README.md
setup.py
easytexminer/__init__.py
easytexminer.egg-info/PKG-INFO
easytexminer.egg-info/SOURCES.txt
easytexminer.egg-info/dependency_links.txt
easytexminer.egg-info/top_level.txt