Metadata-Version: 1.0
Name: easytexminer
Version: 0.0
Summary: EasyTexMiner (An easy-to-use Text Mining Toolkits)
Home-page: UNKNOWN
Author: Haojie Pan,Minghui Qiu
Author-email: haojie.phj@alibaba-inc.com,minghui.qmh@alibaba-inc.com
License: UNKNOWN
Platform: UNKNOWN
